{
    "key": "group_58a6b8598fd05",
    "title": "SEO & Sharing",
    "fields": [
        {
            "key": "field_58a6b864410ed",
            "label": "SEO",
            "name": "",
            "type": "tab",
            "instructions": "",
            "required": 0,
            "conditional_logic": 0,
            "wrapper": {
                "width": "",
                "class": "",
                "id": ""
            },
            "placement": "top",
            "endpoint": 0
        },
        {
            "key": "field_58a6b9cd410ee",
            "label": "Title",
            "name": "seo:title",
            "type": "text",
            "instructions": "",
            "required": 0,
            "conditional_logic": 0,
            "wrapper": {
                "width": "",
                "class": "",
                "id": ""
            },
            "default_value": "",
            "maxlength": "",
            "placeholder": "",
            "prepend": "",
            "append": ""
        },
        {
            "key": "field_58a6b9e9410ef",
            "label": "Description",
            "name": "seo:description",
            "type": "textarea",
            "instructions": "",
            "required": 0,
            "conditional_logic": 0,
            "wrapper": {
                "width": "",
                "class": "",
                "id": ""
            },
            "default_value": "",
            "new_lines": "",
            "maxlength": 160,
            "placeholder": "",
            "rows": 4
        },
        {
            "key": "field_58a6bb1c410f0",
            "label": "Facebook",
            "name": "",
            "type": "tab",
            "instructions": "",
            "required": 0,
            "conditional_logic": 0,
            "wrapper": {
                "width": "",
                "class": "",
                "id": ""
            },
            "placement": "top",
            "endpoint": 0
        },
        {
            "key": "field_58a6bbb1410f4",
            "label": "Type",
            "name": "og:type",
            "type": "select",
            "instructions": "",
            "required": 1,
            "conditional_logic": 0,
            "wrapper": {
                "width": "",
                "class": "",
                "id": ""
            },
            "multiple": 0,
            "allow_null": 0,
            "choices": {
                "website": "Website"
            },
            "default_value": [
                "website"
            ],
            "ui": 0,
            "ajax": 0,
            "placeholder": "",
            "return_format": "value"
        },
        {
            "key": "field_58a6bb23410f1",
            "label": "Title",
            "name": "og:title",
            "type": "text",
            "instructions": "",
            "required": 0,
            "conditional_logic": 0,
            "wrapper": {
                "width": "",
                "class": "",
                "id": ""
            },
            "default_value": "",
            "maxlength": "",
            "placeholder": "",
            "prepend": "",
            "append": ""
        },
        {
            "key": "field_58a6bb54410f3",
            "label": "Description",
            "name": "og:description",
            "type": "textarea",
            "instructions": "",
            "required": 0,
            "conditional_logic": 0,
            "wrapper": {
                "width": "",
                "class": "",
                "id": ""
            },
            "default_value": "",
            "new_lines": "",
            "maxlength": 160,
            "placeholder": "",
            "rows": 4
        },
        {
            "key": "field_58a6cec2ff36b",
            "label": "Image",
            "name": "og:image",
            "type": "image",
            "instructions": "",
            "required": 0,
            "conditional_logic": 0,
            "wrapper": {
                "width": "",
                "class": "",
                "id": ""
            },
            "return_format": "url",
            "preview_size": "thumbnail",
            "library": "all",
            "min_width": "",
            "min_height": "",
            "min_size": "",
            "max_width": "",
            "max_height": "",
            "max_size": "",
            "mime_types": ""
        },
        {
            "key": "field_58a6bbdc410f5",
            "label": "Twitter",
            "name": "",
            "type": "tab",
            "instructions": "",
            "required": 0,
            "conditional_logic": 0,
            "wrapper": {
                "width": "",
                "class": "",
                "id": ""
            },
            "placement": "top",
            "endpoint": 0
        },
        {
            "key": "field_58a6bbe2410f6",
            "label": "Card",
            "name": "twitter:card",
            "type": "select",
            "instructions": "",
            "required": 1,
            "conditional_logic": 0,
            "wrapper": {
                "width": "",
                "class": "",
                "id": ""
            },
            "multiple": 0,
            "allow_null": 0,
            "choices": {
                "summary": "Summary",
                "summary_large_image": "Summary - Large Image"
            },
            "default_value": [
                "summary_large_image"
            ],
            "ui": 0,
            "ajax": 0,
            "placeholder": "",
            "return_format": "value"
        },
        {
            "key": "field_58a6bdd0410f8",
            "label": "Title",
            "name": "twitter:title",
            "type": "text",
            "instructions": "",
            "required": 0,
            "conditional_logic": 0,
            "wrapper": {
                "width": "",
                "class": "",
                "id": ""
            },
            "default_value": "",
            "maxlength": "",
            "placeholder": "",
            "prepend": "",
            "append": ""
        },
        {
            "key": "field_58a6bdde410f9",
            "label": "Description",
            "name": "twitter:description",
            "type": "textarea",
            "instructions": "",
            "required": 0,
            "conditional_logic": 0,
            "wrapper": {
                "width": "",
                "class": "",
                "id": ""
            },
            "default_value": "",
            "new_lines": "",
            "maxlength": 140,
            "placeholder": "",
            "rows": 4
        },
        {
            "key": "field_58a6ceacff36a",
            "label": "Image",
            "name": "twitter:image",
            "type": "image",
            "instructions": "",
            "required": 0,
            "conditional_logic": 0,
            "wrapper": {
                "width": "",
                "class": "",
                "id": ""
            },
            "return_format": "url",
            "preview_size": "thumbnail",
            "library": "all",
            "min_width": "",
            "min_height": "",
            "min_size": "",
            "max_width": "",
            "max_height": "",
            "max_size": "",
            "mime_types": ""
        }
    ],
    "location": [
        [
            {
                "param": "post_type",
                "operator": "==",
                "value": "post"
            }
        ],
        [
            {
                "param": "post_type",
                "operator": "==",
                "value": "page"
            }
        ]
    ],
    "menu_order": 0,
    "position": "normal",
    "style": "default",
    "label_placement": "top",
    "instruction_placement": "label",
    "hide_on_screen": "",
    "active": 1,
    "description": "",
    "modified": 1490628611
}
